{
  "system": {
    "launchOnStartup": false,
    "multipleDisplays": true,
    "serverAnalytics": true,
    "automaticUpdates": true,
    "betaOptIn": false
  },
  "notifications": {
    "connectionEvents": false,
    "disconnectionEvents": false,
    "downloadEvents": true,
    "downloadedEvents": true
  },
  "overlay": { 
    "overlayName": "Floating Top Captions",
    "larivaarGurbani": false,
    "larivaarAssist": false,
    "englishTranslation": true,
    "spanishTranslation": false,
    "punjabiTranslation": false,
    "englishTransliteration": false,
    "hindiTransliteration": false,
    "urduTransliteration": false
  }
}